[{"type": "cfg", "rule": "unreachable", "message": "CFG unreachable: Node 1947254677536", "line": 17, "column": 4, "severity": "medium", "file": "sample_code/example.py"}, {"type": "cfg", "rule": "unreachable", "message": "CFG unreachable: Node 1947254464544", "line": 56, "column": 4, "severity": "medium", "file": "sample_code/example.py"}, {"type": "cfg", "rule": "unreachable", "message": "CFG unreachable: Node 1947254677632", "line": 18, "column": 4, "severity": "medium", "file": "sample_code/example.py"}, {"type": "cfg", "rule": "unreachable", "message": "CFG unreachable: Node 1947254464640", "line": 50, "column": 4, "severity": "medium", "file": "sample_code/example.py"}, {"type": "cfg", "rule": "unreachable", "message": "CFG unreachable: Node loop", "line": 18, "column": 4, "severity": "medium", "file": "sample_code/example.py"}, {"type": "cfg", "rule": "unreachable", "message": "CFG unreachable: Node func_unreachable_code", "line": 55, "column": 0, "severity": "medium", "file": "sample_code/example.py"}, {"type": "cfg", "rule": "unreachable", "message": "CFG unreachable: Node 1947254677824", "line": 20, "column": 4, "severity": "medium", "file": "sample_code/example.py"}, {"type": "cfg", "rule": "unreachable", "message": "CFG unreachable: Node 1947254464832", "line": 51, "column": 4, "severity": "medium", "file": "sample_code/example.py"}, {"type": "cfg", "rule": "unreachable", "message": "CFG unreachable: Node 1947254677920", "line": 19, "column": 8, "severity": "medium", "file": "sample_code/example.py"}, {"type": "cfg", "rule": "unreachable", "message": "CFG unreachable: Node func_run_command", "line": 23, "column": 0, "severity": "medium", "file": "sample_code/example.py"}, {"type": "cfg", "rule": "unreachable", "message": "CFG unreachable: Node 1947254465216", "line": 52, "column": 4, "severity": "medium", "file": "sample_code/example.py"}, {"type": "cfg", "rule": "unreachable", "message": "CFG unreachable: Node 1947254678304", "line": 24, "column": 4, "severity": "medium", "file": "sample_code/example.py"}, {"type": "cfg", "rule": "unreachable", "message": "CFG unreachable: Node 1947254678400", "line": 25, "column": 4, "severity": "medium", "file": "sample_code/example.py"}, {"type": "cfg", "rule": "unreachable", "message": "CFG unreachable: Node func_process_data", "line": 28, "column": 0, "severity": "medium", "file": "sample_code/example.py"}, {"type": "cfg", "rule": "unreachable", "message": "CFG unreachable: Node 1947254678784", "line": 29, "column": 4, "severity": "medium", "file": "sample_code/example.py"}, {"type": "cfg", "rule": "unreachable", "message": "CFG unreachable: Node 1947254678880", "line": 30, "column": 4, "severity": "medium", "file": "sample_code/example.py"}, {"type": "cfg", "rule": "unreachable", "message": "CFG unreachable: Node func_calculate", "line": 10, "column": 0, "severity": "medium", "file": "sample_code/example.py"}, {"type": "cfg", "rule": "unreachable", "message": "CFG unreachable: Node loop", "line": 31, "column": 4, "severity": "medium", "file": "sample_code/example.py"}, {"type": "cfg", "rule": "unreachable", "message": "CFG unreachable: Node 1947254670912", "line": 11, "column": 4, "severity": "medium", "file": "sample_code/example.py"}, {"type": "cfg", "rule": "unreachable", "message": "CFG unreachable: Node 1947254671008", "line": 12, "column": 4, "severity": "medium", "file": "sample_code/example.py"}, {"type": "cfg", "rule": "unreachable", "message": "CFG unreachable: Node func_inefficient_list_builder", "line": 15, "column": 0, "severity": "medium", "file": "sample_code/example.py"}, {"type": "cfg", "rule": "unreachable", "message": "CFG unreachable: Node 1947254466368", "line": 31, "column": 4, "severity": "medium", "file": "sample_code/example.py"}, {"type": "cfg", "rule": "unreachable", "message": "CFG unreachable: Node 1947254466752", "line": 33, "column": 8, "severity": "medium", "file": "sample_code/example.py"}, {"type": "cfg", "rule": "unreachable", "message": "CFG unreachable: Node 1947254466800", "line": 35, "column": 4, "severity": "medium", "file": "sample_code/example.py"}, {"type": "cfg", "rule": "unreachable", "message": "CFG unreachable: Node 1947254467280", "line": 34, "column": 8, "severity": "medium", "file": "sample_code/example.py"}, {"type": "cfg", "rule": "unreachable", "message": "CFG unreachable: Node func_load_object", "line": 42, "column": 0, "severity": "medium", "file": "sample_code/example.py"}, {"type": "cfg", "rule": "unreachable", "message": "CFG unreachable: Node 1947254468288", "line": 43, "column": 4, "severity": "medium", "file": "sample_code/example.py"}, {"type": "cfg", "rule": "unreachable", "message": "CFG unreachable: Node 1947254468912", "line": 118, "column": 4, "severity": "medium", "file": "sample_code/example.py"}, {"type": "cfg", "rule": "unreachable", "message": "CFG unreachable: Node if_cond", "line": 117, "column": 3, "severity": "medium", "file": "sample_code/example.py"}, {"type": "cfg", "rule": "unreachable", "message": "CFG unreachable: Node 1947254469200", "line": 115, "column": 4, "severity": "medium", "file": "sample_code/example.py"}, {"type": "cfg", "rule": "unreachable", "message": "CFG unreachable: Node 1947254469296", "line": 109, "column": 4, "severity": "medium", "file": "sample_code/example.py"}, {"type": "cfg", "rule": "unreachable", "message": "CFG unreachable: Node 1947254469392", "line": 106, "column": 4, "severity": "medium", "file": "sample_code/example.py"}, {"type": "cfg", "rule": "unreachable", "message": "CFG unreachable: Node 1947254469488", "line": 105, "column": 4, "severity": "medium", "file": "sample_code/example.py"}, {"type": "cfg", "rule": "unreachable", "message": "CFG unreachable: Node 1947254469584", "line": 102, "column": 4, "severity": "medium", "file": "sample_code/example.py"}, {"type": "cfg", "rule": "unreachable", "message": "CFG unreachable: Node 1947254469680", "line": 101, "column": 4, "severity": "medium", "file": "sample_code/example.py"}, {"type": "cfg", "rule": "unreachable", "message": "CFG unreachable: Node 1947254469776", "line": 98, "column": 4, "severity": "medium", "file": "sample_code/example.py"}, {"type": "cfg", "rule": "unreachable", "message": "CFG unreachable: Node 1947254469872", "line": 97, "column": 4, "severity": "medium", "file": "sample_code/example.py"}, {"type": "cfg", "rule": "unreachable", "message": "CFG unreachable: Node 1947254469968", "line": 44, "column": 4, "severity": "medium", "file": "sample_code/example.py"}, {"type": "cfg", "rule": "unreachable", "message": "CFG unreachable: Node func_unused_variables", "line": 48, "column": 0, "severity": "medium", "file": "sample_code/example.py"}, {"type": "cfg", "rule": "unreachable", "message": "CFG unreachable: Node 1947254470256", "line": 49, "column": 4, "severity": "medium", "file": "sample_code/example.py"}, {"type": "cfg", "rule": "unreachable", "message": "CFG unreachable: Node 1947254470352", "line": 94, "column": 4, "severity": "medium", "file": "sample_code/example.py"}, {"type": "cfg", "rule": "unreachable", "message": "CFG unreachable: Node 1947254470448", "line": 93, "column": 4, "severity": "medium", "file": "sample_code/example.py"}, {"type": "cfg", "rule": "unreachable", "message": "CFG unreachable: Node 1947254470544", "line": 92, "column": 4, "severity": "medium", "file": "sample_code/example.py"}, {"type": "cfg", "rule": "unreachable", "message": "CFG unreachable: Node 1947254470640", "line": 90, "column": 4, "severity": "medium", "file": "sample_code/example.py"}, {"type": "cfg", "rule": "unreachable", "message": "CFG unreachable: Node func_main", "line": 89, "column": 0, "severity": "medium", "file": "sample_code/example.py"}, {"type": "cfg", "rule": "unreachable", "message": "CFG unreachable: Node 1947254470928", "line": 86, "column": 4, "severity": "medium", "file": "sample_code/example.py"}, {"type": "cfg", "rule": "unreachable", "message": "CFG unreachable: Node 1947254471024", "line": 82, "column": 4, "severity": "medium", "file": "sample_code/example.py"}, {"type": "cfg", "rule": "unreachable", "message": "CFG unreachable: Node 1947254471120", "line": 79, "column": 4, "severity": "medium", "file": "sample_code/example.py"}, {"type": "cfg", "rule": "unreachable", "message": "CFG unreachable: Node 1947254471216", "line": 78, "column": 4, "severity": "medium", "file": "sample_code/example.py"}, {"type": "cfg", "rule": "unreachable", "message": "CFG unreachable: Node 1947254471312", "line": 77, "column": 4, "severity": "medium", "file": "sample_code/example.py"}, {"type": "cfg", "rule": "unreachable", "message": "CFG unreachable: Node func_nested_comprehension", "line": 76, "column": 0, "severity": "medium", "file": "sample_code/example.py"}, {"type": "cfg", "rule": "unreachable", "message": "CFG unreachable: Node 1947254471600", "line": 73, "column": 4, "severity": "medium", "file": "sample_code/example.py"}, {"type": "cfg", "rule": "unreachable", "message": "CFG unreachable: Node 1947254471696", "line": 69, "column": 4, "severity": "medium", "file": "sample_code/example.py"}, {"type": "cfg", "rule": "unreachable", "message": "CFG unreachable: Node 1947254471792", "line": 68, "column": 4, "severity": "medium", "file": "sample_code/example.py"}, {"type": "cfg", "rule": "unreachable", "message": "CFG unreachable: Node func_exception_handling", "line": 67, "column": 0, "severity": "medium", "file": "sample_code/example.py"}, {"type": "cfg", "rule": "unreachable", "message": "CFG unreachable: Node 1947254472032", "line": 64, "column": 8, "severity": "medium", "file": "sample_code/example.py"}, {"type": "cfg", "rule": "unreachable", "message": "CFG unreachable: Node loop", "line": 63, "column": 4, "severity": "medium", "file": "sample_code/example.py"}, {"type": "cfg", "rule": "unreachable", "message": "CFG unreachable: Node 1947254472272", "line": 63, "column": 4, "severity": "medium", "file": "sample_code/example.py"}, {"type": "cfg", "rule": "unreachable", "message": "CFG unreachable: Node 1947254472368", "line": 62, "column": 4, "severity": "medium", "file": "sample_code/example.py"}, {"type": "cfg", "rule": "unreachable", "message": "CFG unreachable: Node func_infinite_loop", "line": 61, "column": 0, "severity": "medium", "file": "sample_code/example.py"}, {"type": "cfg", "rule": "unreachable", "message": "CFG unreachable: Node 1947254464352", "line": 57, "column": 4, "severity": "medium", "file": "sample_code/example.py"}, {"type": "cfg", "rule": "unreachable", "message": "CFG unreachable: Node 1947254677440", "line": 16, "column": 4, "severity": "medium", "file": "sample_code/example.py"}, {"type": "cfg", "rule": "unreachable", "message": "CFG unreachable: Node 1947254472656", "line": 58, "column": 4, "severity": "medium", "file": "sample_code/example.py"}, {"type": "cfg", "rule": "exception_paths", "message": "CFG exception paths: Node 1947254471696", "line": 69, "column": 4, "severity": "medium", "file": "sample_code/example.py"}, {"type": "security", "rule": "unsafe_eval", "message": "Potentially unsafe eval() function", "line": 12, "column": 11, "severity": "high", "file": "sample_code/example.py"}, {"type": "security", "rule": "unsafe_os.system", "message": "Command injection risk with os.system()", "line": 25, "column": 11, "severity": "high", "file": "sample_code/example.py"}, {"type": "security", "rule": "unsafe_pickle.load", "message": "Deserialization vulnerability with pickle", "line": 45, "column": 15, "severity": "high", "file": "sample_code/example.py"}, {"type": "performance", "rule": "expensive_operation_in_loop", "message": "Expensive operation copy() called inside a loop", "line": 33, "column": 20, "severity": "medium", "file": "sample_code/example.py"}]